faultier/DashApp.py
faultier/FaulterVis.py
faultier/Faultier.py
faultier/FaultierTool.py
faultier/GlitchDataCollection.py
faultier/GlitchDatabase.py
faultier/LivePlot.py
faultier/RandomOrderGenerator.py
faultier/__init__.py
faultier/faultier_pb2.py
faultier/docs/sideview.svg
faultier/docs/topview.svg
faultier/example_firmware/nrf52832_xxaa.hex
faultier/example_firmware/s132_nrf52_7.2.0_softdevice.hex
faultier-0.2.2.dist-info/METADATA
faultier-0.2.2.dist-info/WHEEL
faultier-0.2.2.dist-info/entry_points.txt
faultier-0.2.2.dist-info/top_level.txt
faultier-0.2.2.dist-info/RECORD
