Metadata-Version: 2.4
Name: faultier
Version: 0.2.2
Summary: A library to control the Faultier fault-injection tool.
Author-email: Thomas 'stacksmashing' Roth <code@stacksmashing.net>
Requires-Dist: pyserial
Requires-Dist: pyusb
Requires-Dist: plotly
Requires-Dist: google
Requires-Dist: protobuf==5.29.5
Requires-Dist: tqdm
Requires-Dist: matplotlib
Requires-Dist: jupyter
Requires-Dist: dash>=2.14.0
Requires-Dist: plotly>=5.17.0
Requires-Dist: pandas>=2.0.0
Requires-Dist: dash-bootstrap-components>=1.5.0
Requires-Dist: numpy>=1.24.0
Requires-Dist: pyocd-faultier
